django_layui29/__init__.py
django_layui29/admin.py
django_layui29/apps.py
django_layui29/form.py
django_layui29/migrations/__init__.py
django_layui29/models.py
django_layui29/static/layui29/css/center.css
django_layui29/static/layui29/css/global.css
django_layui29/static/layui29/css/layui.css
django_layui29/static/layui29/font/iconfont.woff2
django_layui29/static/layui29/js/base.js
django_layui29/static/layui29/js/js.cookie.min.js
django_layui29/static/layui29/layui.js
django_layui29/templates/layui29/base.html
django_layui29/templates/layui29/component/base/header.html
django_layui29/templates/layui29/component/base/left_nav.html
django_layui29/templates/layui29/component/tables.html
django_layui29/templates/layui29/layout/admin.html
django_layui29/templates/layui29/layout/center.html
django_layui29/templates/layui29/layout/normal.html
django_layui29/tests.py
django_layui29/utils.py
django_layui29/views.py
django_layui29-0.4.5.dist-info/LICENSE
django_layui29-0.4.5.dist-info/METADATA
django_layui29-0.4.5.dist-info/WHEEL
django_layui29-0.4.5.dist-info/RECORD
