Metadata-Version: 2.3
Name: django_layui29
Version: 0.4.5
Summary: django template based on layui2.9
Author: svtter
Author-email: svtter@163.com
Requires-Python: >=3.9,<4.0
Classifier: Programming Language :: Python :: 3
Classifier: Programming Language :: Python :: 3.9
Classifier: Programming Language :: Python :: 3.10
Classifier: Programming Language :: Python :: 3.11
Classifier: Programming Language :: Python :: 3.12
Classifier: Programming Language :: Python :: 3.13
Requires-Dist: django (<6.0)
Project-URL: bugs, https://github.com/Svtter/django_layui29/issues
Project-URL: changelog, https://github.com/Svtter/django_layui29/blob/master/CHANGELOG.md
Project-URL: homepage, https://github.com/Svtter/django_layui29
Project-URL: repository, https://github.com/Svtter/django_layui29.git
